{
    "key": "group_675fb313b326b",
    "title": "Hero Banner",
    "fields": [
        {
            "key": "field_6760f7c4b0295",
            "label": "Block Settings",
            "name": "block_settings",
            "aria-label": "",
            "type": "clone",
            "instructions": "",
            "required": 0,
            "conditional_logic": 0,
            "wrapper": {
                "width": "",
                "class": "",
                "id": ""
            },
            "clone": [
                "group_6760f7465f6f3"
            ],
            "display": "seamless",
            "layout": "block",
            "prefix_label": 0,
            "prefix_name": 0
        },
        {
            "key": "field_675fb3140044c",
            "label": "Style",
            "name": "style",
            "aria-label": "",
            "type": "select",
            "instructions": "",
            "required": 0,
            "conditional_logic": 0,
            "wrapper": {
                "width": "",
                "class": "",
                "id": ""
            },
            "choices": {
                "image": "Image"
            },
            "default_value": "image",
            "return_format": "value",
            "multiple": 0,
            "allow_null": 0,
            "allow_in_bindings": 1,
            "ui": 0,
            "ajax": 0,
            "placeholder": ""
        },
        {
            "key": "field_675fb3d83eb56",
            "label": "Title",
            "name": "title",
            "aria-label": "",
            "type": "text",
            "instructions": "",
            "required": 0,
            "conditional_logic": 0,
            "wrapper": {
                "width": "",
                "class": "",
                "id": ""
            },
            "default_value": "",
            "maxlength": "",
            "allow_in_bindings": 0,
            "placeholder": "",
            "prepend": "",
            "append": ""
        },
        {
            "key": "field_675fb3e73eb57",
            "label": "Content",
            "name": "content",
            "aria-label": "",
            "type": "textarea",
            "instructions": "",
            "required": 0,
            "conditional_logic": 0,
            "wrapper": {
                "width": "",
                "class": "",
                "id": ""
            },
            "default_value": "",
            "maxlength": "",
            "allow_in_bindings": 0,
            "rows": 4,
            "placeholder": "",
            "new_lines": "br"
        },
        {
            "key": "field_675fb4043eb58",
            "label": "CTA",
            "name": "cta",
            "aria-label": "",
            "type": "link",
            "instructions": "",
            "required": 0,
            "conditional_logic": 0,
            "wrapper": {
                "width": "50",
                "class": "",
                "id": ""
            },
            "return_format": "array",
            "allow_in_bindings": 0
        },
        {
            "key": "field_67712cd745aca",
            "label": "CTA Theme",
            "name": "cta_theme",
            "aria-label": "",
            "type": "editor_palette",
            "instructions": "",
            "required": 0,
            "conditional_logic": 0,
            "wrapper": {
                "width": "50",
                "class": "",
                "id": ""
            },
            "default_value": "theme-white",
            "allowed_colors": [
                "theme-white",
                "theme-blue",
                "theme-teal"
            ],
            "exclude_colors": "",
            "return_format": "slug",
            "allow_in_bindings": 0
        },
        {
            "key": "field_675fb4233eb59",
            "label": "Image",
            "name": "image",
            "aria-label": "",
            "type": "image",
            "instructions": "",
            "required": 0,
            "conditional_logic": [
                [
                    {
                        "field": "field_675fb3140044c",
                        "operator": "==",
                        "value": "image"
                    }
                ]
            ],
            "wrapper": {
                "width": "",
                "class": "",
                "id": ""
            },
            "return_format": "array",
            "library": "all",
            "min_width": "",
            "min_height": "",
            "min_size": "",
            "max_width": "",
            "max_height": "",
            "max_size": "",
            "mime_types": "",
            "allow_in_bindings": 0,
            "preview_size": "medium"
        }
    ],
    "location": [
        [
            {
                "param": "block",
                "operator": "==",
                "value": "acf\/hero-banner"
            }
        ]
    ],
    "menu_order": 0,
    "position": "normal",
    "style": "default",
    "label_placement": "top",
    "instruction_placement": "label",
    "hide_on_screen": "",
    "active": true,
    "description": "",
    "show_in_rest": 0,
    "modified": 1735661221
}
